odoo/addons/ssi_transaction_win_lost_mixin/README.rst
odoo/addons/ssi_transaction_win_lost_mixin/__init__.py
odoo/addons/ssi_transaction_win_lost_mixin/__manifest__.py
odoo/addons/ssi_transaction_win_lost_mixin/demo/base_lost_reason_demo.xml
odoo/addons/ssi_transaction_win_lost_mixin/i18n/ssi_transaction_win_lost_mixin.pot
odoo/addons/ssi_transaction_win_lost_mixin/models/__init__.py
odoo/addons/ssi_transaction_win_lost_mixin/models/base_lost_reason.py
odoo/addons/ssi_transaction_win_lost_mixin/models/ir_model.py
odoo/addons/ssi_transaction_win_lost_mixin/models/mixin_transaction_win_lost.py
odoo/addons/ssi_transaction_win_lost_mixin/security/ir.model.access.csv
odoo/addons/ssi_transaction_win_lost_mixin/static/description/icon.png
odoo/addons/ssi_transaction_win_lost_mixin/templates/mixin_transaction_win_lost_templates.xml
odoo/addons/ssi_transaction_win_lost_mixin/views/base_lost_reason_views.xml
odoo/addons/ssi_transaction_win_lost_mixin/views/ir_model_views.xml
odoo/addons/ssi_transaction_win_lost_mixin/wizards/__init__.py
odoo/addons/ssi_transaction_win_lost_mixin/wizards/base_select_lost_reason.py
odoo/addons/ssi_transaction_win_lost_mixin/wizards/base_select_lost_reason_views.xml
odoo14_addon_ssi_transaction_win_lost_mixin-14.0.1.9.1.dist-info/METADATA
odoo14_addon_ssi_transaction_win_lost_mixin-14.0.1.9.1.dist-info/WHEEL
odoo14_addon_ssi_transaction_win_lost_mixin-14.0.1.9.1.dist-info/top_level.txt
odoo14_addon_ssi_transaction_win_lost_mixin-14.0.1.9.1.dist-info/RECORD
